text2class/__init__.py
text2class/classification.py
text2class/modeling.py
text2class/modeling_test.py
text2class/optimization.py
text2class/optimization_test.py
text2class/text_classifier.py
text2class/tokenization.py
text2class/tokenization_test.py
text2class-0.0.4.dist-info/LICENSE
text2class-0.0.4.dist-info/METADATA
text2class-0.0.4.dist-info/WHEEL
text2class-0.0.4.dist-info/top_level.txt
text2class-0.0.4.dist-info/RECORD
