Metadata-Version: 2.1
Name: text2class
Version: 0.0.4
Summary: Multi-class text categorization using state-of-the-art pre-trained contextualized language models, e.g. BERT.
Home-page: https://github.com/artitw/text2class
Author: Artit Wangperawong
Author-email: artitw@gmail.com
License: UNKNOWN
Keywords: bert nlp text classification data science machine learning
Platform: UNKNOWN
Classifier: Programming Language :: Python :: 3
Classifier: License :: OSI Approved :: Apache Software License
Classifier: Operating System :: OS Independent
Requires-Dist: tensorflow (==1.15.2)
Requires-Dist: tensorflow-hub
Requires-Dist: pandas
